massdns
